[ { "name" : "BACKSPACE",
"text" : "8",
"value" : 8},
{ "name" : "TAB",
"text" : "9",
"value" : 9},
{ "name" : "ENTER",
"text" : "13",
"value" : 13},
{ "name" : "SHIFT",
"text" : "16",
"value" : 16},
{ "name" : "CTRL",
"text" : "17",
"value" : 17},
{ "name" : "ALT",
"text" : "18",
"value" : 18},
{ "name" : "PAUSE",
"text" : "19",
"value" : 19},
{ "name" : "BREAK",
"text" : "19",
"value" : 19},
{ "name" : "CAPSLOCK",
"text" : "20",
"value" : 20},
{ "name" : "ESCAPE",
"text" : "27",
"value" : 27},
{ "name" : "SPACE",
"text" : "32",
"value" : 32},
{ "name" : "PAGEUP",
"text" : "33",
"value" : 33},
{ "name" : "PAGEDOWN",
"text" : "34",
"value" : 34},
{ "name" : "END",
"text" : "35",
"value" : 35},
{ "name" : "HOME",
"text" : "36",
"value" : 36},
{ "name" : "LEFT",
"text" : "37",
"value" : 37},
{ "name" : "UP",
"text" : "38",
"value" : 38},
{ "name" : "RIGHT",
"text" : "39",
"value" : 39},
{ "name" : "DOWN",
"text" : "40",
"value" : 40},
{ "name" : "INSERT",
"text" : "45",
"value" : 45},
{ "name" : "DELETE",
"text" : "46",
"value" : 46},
{ "name" : "N0",
"text" : "48",
"value" : 48},
{ "name" : "N1",
"text" : "49",
"value" : 49},
{ "name" : "N2",
"text" : "50",
"value" : 50},
{ "name" : "N3",
"text" : "51",
"value" : 51},
{ "name" : "N4",
"text" : "52",
"value" : 52},
{ "name" : "N5",
"text" : "53",
"value" : 53},
{ "name" : "N6",
"text" : "54",
"value" : 54},
{ "name" : "N7",
"text" : "55",
"value" : 55},
{ "name" : "N8",
"text" : "56",
"value" : 56},
{ "name" : "N9",
"text" : "57",
"value" : 57},
{ "name" : "A",
"text" : "65",
"value" : 65},
{ "name" : "B",
"text" : "66",
"value" : 66},
{ "name" : "C",
"text" : "67",
"value" : 67},
{ "name" : "D",
"text" : "68",
"value" : 68},
{ "name" : "E",
"text" : "69",
"value" : 69},
{ "name" : "F",
"text" : "70",
"value" : 70},
{ "name" : "G",
"text" : "71",
"value" : 71},
{ "name" : "H",
"text" : "72",
"value" : 72},
{ "name" : "I",
"text" : "73",
"value" : 73},
{ "name" : "J",
"text" : "74",
"value" : 74},
{ "name" : "K",
"text" : "75",
"value" : 75},
{ "name" : "L",
"text" : "76",
"value" : 76},
{ "name" : "M",
"text" : "77",
"value" : 77},
{ "name" : "N",
"text" : "78",
"value" : 78},
{ "name" : "O",
"text" : "79",
"value" : 79},
{ "name" : "P",
"text" : "80",
"value" : 80},
{ "name" : "Q",
"text" : "81",
"value" : 81},
{ "name" : "R",
"text" : "82",
"value" : 82},
{ "name" : "S",
"text" : "83",
"value" : 83},
{ "name" : "T",
"text" : "84",
"value" : 84},
{ "name" : "U",
"text" : "85",
"value" : 85},
{ "name" : "V",
"text" : "86",
"value" : 86},
{ "name" : "W",
"text" : "87",
"value" : 87},
{ "name" : "X",
"text" : "88",
"value" : 88},
{ "name" : "Y",
"text" : "89",
"value" : 89},
{ "name" : "Z",
"text" : "90",
"value" : 90},
{ "name" : "LEFTWINDOWKEY",
"text" : "91",
"value" : 91},
{ "name" : "RIGHTWINDOWKEY",
"text" : "92",
"value" : 92},
{ "name" : "SELECTKEY",
"text" : "93",
"value" : 93},
{ "name" : "NUMPAD0",
"text" : "96",
"value" : 96},
{ "name" : "NUMPAD1",
"text" : "97",
"value" : 97},
{ "name" : "NUMPAD2",
"text" : "98",
"value" : 98},
{ "name" : "NUMPAD3",
"text" : "99",
"value" : 99},
{ "name" : "NUMPAD4",
"text" : "100",
"value" : 100},
{ "name" : "NUMPAD5",
"text" : "101",
"value" : 101},
{ "name" : "NUMPAD6",
"text" : "102",
"value" : 102},
{ "name" : "NUMPAD7",
"text" : "103",
"value" : 103},
{ "name" : "NUMPAD8",
"text" : "104",
"value" : 104},
{ "name" : "NUMPAD9",
"text" : "105",
"value" : 105},
{ "name" : "MULTIPLY",
"text" : "106",
"value" : 106},
{ "name" : "ADD",
"text" : "107",
"value" : 107},
{ "name" : "SUBTRACT",
"text" : "109",
"value" : 109},
{ "name" : "DECIMALPOINT",
"text" : "110",
"value" : 110},
{ "name" : "DIVIDE",
"text" : "111",
"value" : 111},
{ "name" : "F1",
"text" : "112",
"value" : 112},
{ "name" : "F2",
"text" : "113",
"value" : 113},
{ "name" : "F3",
"text" : "114",
"value" : 114},
{ "name" : "F4",
"text" : "115",
"value" : 115},
{ "name" : "F5",
"text" : "116",
"value" : 116},
{ "name" : "F6",
"text" : "117",
"value" : 117},
{ "name" : "F7",
"text" : "118",
"value" : 118},
{ "name" : "F8",
"text" : "119",
"value" : 119},
{ "name" : "F9",
"text" : "120",
"value" : 120},
{ "name" : "F10",
"text" : "121",
"value" : 121},
{ "name" : "F11",
"text" : "122",
"value" : 122},
{ "name" : "F12",
"text" : "123",
"value" : 123},
{ "name" : "NUMLOCK",
"text" : "144",
"value" : 144},
{ "name" : "SCROLLLOCK",
"text" : "145",
"value" : 145},
{ "name" : "SEMICOLON",
"text" : "186",
"value" : 186},
{ "name" : "EQUALSIGN",
"text" : "187",
"value" : 187},
{ "name" : "COMMA",
"text" : "188",
"value" : 188},
{ "name" : "DASH",
"text" : "189",
"value" : 189},
{ "name" : "PERIOD",
"text" : "190",
"value" : 190},
{ "name" : "FORWARDSLASH",
"text" : "191",
"value" : 191},
{ "name" : "GRAVEACCENT",
"text" : "192",
"value" : 192},
{ "name" : "OPENBRACKET",
"text" : "219",
"value" : 219},
{ "name" : "BACKSLASH",
"text" : "220",
"value" : 220},
{ "name" : "CLOSEBRACKET",
"text" : "221",
"value" : 221},
{ "name" : "SINGLEQUOTE",
"text" : "222",
"value" : 222},
{ "name" : "TOTAL",
"text" : "256",
"value" : 256} ]