{ "location" : "akra.render",
"variables" : { "private" : { "_pDataBuffer" : { "location" : "akra.render.RenderDataCollection",
"type" : "IVertexBuffer"},
"_pEngine" : { "location" : "akra.render.RenderDataCollection",
"type" : "IEngine"},
"_eDataOptions" : { "location" : "akra.render.RenderDataCollection",
"type" : "ERenderDataBufferOptions"},
"_pDataArray" : { "location" : "akra.render.RenderDataCollection",
"type" : "IRenderData[  ]"}}},
"getters" : { "buffer" : { "type" : "IVertexBuffer",
"isInline" : false,
"location" : "akra.render.RenderDataCollection"},
"length" : { "type" : "number",
"isInline" : false,
"location" : "akra.render.RenderDataCollection"},
"byteLength" : { "type" : "number",
"isInline" : false,
"location" : "akra.render.RenderDataCollection"}},
"constructors" : [ { "comments" : [  ],
"location" : "akra.render.RenderDataCollection",
"arguments" : [ { "name" : "pEngine",
"isOptional" : false,
"type" : "IEngine"},
{ "name" : "eOptions",
"isOptional" : true,
"type" : "ERenderDataBufferOptions"} ]} ],
"functions" : { "clone" : { "comments" : [  ],
"location" : "akra.render.RenderDataCollection",
"arguments" : [ { "name" : "pSrc",
"isOptional" : false,
"type" : "IRenderDataCollection"} ],
"type" : "bool",
"isInline" : false},
"getEngine" : { "comments" : [  ],
"location" : "akra.render.RenderDataCollection",
"arguments" : [  ],
"type" : "IEngine",
"isInline" : false},
"getOptions" : { "comments" : [  ],
"location" : "akra.render.RenderDataCollection",
"arguments" : [  ],
"type" : "ERenderDataBufferOptions",
"isInline" : false},
"getData" : { "comments" : [  ],
"location" : "akra.render.RenderDataCollection",
"arguments" : [ { "name" : "iOffset",
"isOptional" : false,
"type" : "number"} ],
"type" : "IVertexData",
"isInline" : false},
"_allocateData" : { "comments" : [  ],
"location" : "akra.render.RenderDataCollection",
"arguments" : [ { "name" : "pDeclData",
"isOptional" : false,
"type" : "[  ]"},
{ "name" : "pData",
"isOptional" : false,
"type" : "ArrayBuffer"} ],
"type" : "IVertexData",
"isInline" : false},
"allocateData" : { "comments" : [  ],
"location" : "akra.render.RenderDataCollection",
"arguments" : [ { "name" : "pDeclData",
"isOptional" : false,
"type" : "[  ]"},
{ "name" : "pData",
"isOptional" : false,
"type" : "ArrayBuffer"},
{ "name" : "isCommon",
"isOptional" : true,
"type" : "bool"} ],
"type" : "number",
"isInline" : false},
"getDataLocation" : { "comments" : [  ],
"location" : "akra.render.RenderDataCollection",
"arguments" : [ { "name" : "sSemantics",
"isOptional" : false,
"type" : "string"} ],
"type" : "number",
"isInline" : false},
"createDataBuffer" : { "comments" : [  ],
"location" : "akra.render.RenderDataCollection",
"arguments" : [  ],
"type" : "bool",
"isInline" : false},
"getRenderData" : { "comments" : [  ],
"location" : "akra.render.RenderDataCollection",
"arguments" : [ { "name" : "iSubset",
"isOptional" : false,
"type" : "number"} ],
"type" : "IRenderData",
"isInline" : false},
"getEmptyRenderData" : { "comments" : [  ],
"location" : "akra.render.RenderDataCollection",
"arguments" : [ { "name" : "ePrimType",
"isOptional" : false,
"type" : "EPrimitiveTypes"},
{ "name" : "eOptions",
"isOptional" : true,
"type" : "ERenderDataBufferOptions"} ],
"type" : "IRenderData",
"isInline" : false},
"_draw" : { "comments" : [  ],
"location" : "akra.render.RenderDataCollection",
"arguments" : [  ],
"type" : "void",
"isInline" : false},
"destroy" : { "comments" : [  ],
"location" : "akra.render.RenderDataCollection",
"arguments" : [  ],
"type" : "void",
"isInline" : false},
"setup" : { "comments" : [  ],
"location" : "akra.render.RenderDataCollection",
"arguments" : [ { "name" : "eOptions",
"isOptional" : true,
"type" : "ERenderDataBufferOptions"} ],
"type" : "void",
"isInline" : false}}}