{ "location" : "akra.scene.light",
"variables" : { "protected" : { "_isShadowCaster" : { "location" : "akra.scene.light.LightPoint",
"type" : "bool"},
"_isEnabled" : { "location" : "akra.scene.light.LightPoint",
"type" : "bool"},
"_iMaxShadowResolution" : { "location" : "akra.scene.light.LightPoint",
"type" : "number"},
"_eLightType" : { "location" : "akra.scene.light.LightPoint",
"type" : "ELightTypes"},
"_pOptimizedCameraFrustum" : { "location" : "akra.scene.light.LightPoint",
"type" : "IFrustum"}}},
"getters" : { "lightType" : { "type" : "ELightTypes",
"isInline" : false,
"location" : "akra.scene.light.LightPoint"},
"enabled" : { "type" : "bool",
"isInline" : false,
"location" : "akra.scene.light.LightPoint"},
"params" : { "type" : "ILightParameters",
"isInline" : false,
"location" : "akra.scene.light.LightPoint"},
"isShadowCaster" : { "type" : "bool",
"isInline" : false,
"location" : "akra.scene.light.LightPoint"},
"lightingDistance" : { "type" : "number",
"isInline" : false,
"location" : "akra.scene.light.LightPoint"},
"optimizedCameraFrustum" : { "type" : "IFrustum",
"isInline" : false,
"location" : "akra.scene.light.LightPoint"}},
"constructors" : [ { "comments" : [  ],
"location" : "akra.scene.light.LightPoint",
"arguments" : [ { "name" : "pScene",
"isOptional" : false,
"type" : "IScene3d"},
{ "name" : "eType",
"isOptional" : true,
"type" : "ELightTypes"} ]} ],
"setters" : { "enabled" : { "type" : "bool",
"inline" : false,
"location" : "akra.scene.light.LightPoint"},
"isShadowCaster" : { "type" : "bool",
"inline" : false,
"location" : "akra.scene.light.LightPoint"},
"lightingDistance" : { "type" : "number",
"inline" : false,
"location" : "akra.scene.light.LightPoint"}},
"functions" : { "create" : { "comments" : [  ],
"location" : "akra.scene.light.LightPoint",
"arguments" : [ { "name" : "isShadowCaster",
"isOptional" : true,
"type" : "bool"},
{ "name" : "iMaxShadowResolution",
"isOptional" : true,
"type" : "number"} ],
"type" : "bool",
"isInline" : false},
"_prepareForLighting" : { "comments" : [  ],
"location" : "akra.scene.light.LightPoint",
"arguments" : [ { "name" : "pCamera",
"isOptional" : false,
"type" : "ICamera"} ],
"type" : "bool",
"isInline" : false},
"_calculateShadows" : { "comments" : [  ],
"location" : "akra.scene.light.LightPoint",
"arguments" : [  ],
"type" : "void",
"isInline" : false}}}