{ "location" : "akra.terrain",
"variables" : { "protected" : { "_pEngine" : { "location" : "akra.terrain.Terrain",
"type" : "akra.IEngine"},
"_pWorldExtents" : { "location" : "akra.terrain.Terrain",
"type" : "akra.IRect3d"},
"_iSectorCountX" : { "location" : "akra.terrain.Terrain",
"type" : "uint"},
"_iSectorCountY" : { "location" : "akra.terrain.Terrain",
"type" : "uint"},
"_pSectorArray" : { "location" : "akra.terrain.Terrain",
"type" : "akra.ITerrainSection"},
"_pDataFactory" : { "location" : "akra.terrain.Terrain",
"type" : "akra.IRenderDataCollection"},
"_v2fSectorSize" : { "location" : "akra.terrain.Terrain",
"type" : "akra.IVec2"},
"_iSectorShift" : { "location" : "akra.terrain.Terrain",
"type" : "uint"},
"_iSectorUnits" : { "location" : "akra.terrain.Terrain",
"type" : "uint"},
"_iSectorVerts" : { "location" : "akra.terrain.Terrain",
"type" : "uint"},
"_iTableWidth" : { "location" : "akra.terrain.Terrain",
"type" : "uint"},
"_iTableHeight" : { "location" : "akra.terrain.Terrain",
"type" : "uint"},
"_pHeightTable" : { "location" : "akra.terrain.Terrain",
"type" : "Float32Array"},
"_bUseVertexNormal" : { "location" : "akra.terrain.Terrain",
"type" : "bool"},
"_pDefaultRenderMethod" : { "location" : "akra.terrain.Terrain",
"type" : "akra.IRenderMethod"},
"_pRenderMethod" : { "location" : "akra.terrain.Terrain",
"type" : "akra.IRenderMethod"},
"_pDefaultScreen" : { "location" : "akra.terrain.Terrain",
"type" : "akra.IRenderableObject"},
"_isCreate" : { "location" : "akra.terrain.Terrain",
"type" : "bool"},
"_bManualMegaTextureInit" : { "location" : "akra.terrain.Terrain",
"type" : "bool"},
"_bShowMegaTexture" : { "location" : "akra.terrain.Terrain",
"type" : "bool"},
"_bMegaTextureCreated" : { "location" : "akra.terrain.Terrain",
"type" : "bool"},
"_sSurfaceTextures" : { "location" : "akra.terrain.Terrain",
"type" : "string"}},
"private" : { "_v3fWorldSize" : { "location" : "akra.terrain.Terrain",
"type" : "akra.IVec3"},
"_v3fMapScale" : { "location" : "akra.terrain.Terrain",
"type" : "akra.IVec3"},
"_pNormalMapTexture" : { "location" : "akra.terrain.Terrain",
"type" : "akra.ITexture"},
"_pNormalMapImage" : { "location" : "akra.terrain.Terrain",
"type" : "akra.IImg"},
"_pBaseNormalTexture" : { "location" : "akra.terrain.Terrain",
"type" : "akra.ITexture"},
"_pBaseNormalImage" : { "location" : "akra.terrain.Terrain",
"type" : "akra.IImg"},
"_pHeightMapTexture" : { "location" : "akra.terrain.Terrain",
"type" : "akra.ITexture"},
"_pTempNormalColor" : { "location" : "akra.terrain.Terrain",
"type" : "akra.IColor"},
"_pMegaTexures" : { "location" : "akra.terrain.Terrain",
"type" : "akra.IMegaTexture"},
"_fMaxHeight" : { "location" : "akra.terrain.Terrain",
"type" : "float"},
"_f2DDiagonal" : { "location" : "akra.terrain.Terrain",
"type" : "float"}}},
"constructors" : [ { "comments" : [  ],
"location" : "akra.terrain.Terrain",
"arguments" : [ { "name" : "pScene",
"isOptional" : false,
"type" : "akra.IScene3d"},
{ "name" : "eType",
"isOptional" : true,
"type" : "akra.EEntityTypes"} ]} ],
"getters" : { "dataFactory" : { "type" : "akra.IRenderDataCollection",
"isInline" : true,
"location" : "akra.terrain.Terrain"},
"worldExtents" : { "type" : "akra.IRect3d",
"isInline" : true,
"location" : "akra.terrain.Terrain"},
"worldSize" : { "type" : "akra.IVec3",
"isInline" : true,
"location" : "akra.terrain.Terrain"},
"mapScale" : { "type" : "akra.IVec3",
"isInline" : true,
"location" : "akra.terrain.Terrain"},
"sectorCountX" : { "type" : "uint",
"isInline" : true,
"location" : "akra.terrain.Terrain"},
"sectorCountY" : { "type" : "uint",
"isInline" : true,
"location" : "akra.terrain.Terrain"},
"sectorSize" : { "type" : "akra.IVec2",
"isInline" : true,
"location" : "akra.terrain.Terrain"},
"tableWidth" : { "type" : "uint",
"isInline" : true,
"location" : "akra.terrain.Terrain"},
"tableHeight" : { "type" : "uint",
"isInline" : true,
"location" : "akra.terrain.Terrain"},
"sectorShift" : { "type" : "uint",
"isInline" : true,
"location" : "akra.terrain.Terrain"},
"maxHeight" : { "type" : "float",
"isInline" : true,
"location" : "akra.terrain.Terrain"},
"terrain2DLength" : { "type" : "float",
"isInline" : true,
"location" : "akra.terrain.Terrain"},
"megaTexture" : { "type" : "akra.IMegaTexture",
"isInline" : true,
"location" : "akra.terrain.Terrain"},
"manualMegaTextureInit" : { "type" : "bool",
"isInline" : true,
"location" : "akra.terrain.Terrain"},
"showMegaTexture" : { "type" : "bool",
"isInline" : true,
"location" : "akra.terrain.Terrain"}},
"functions" : { "isCreate" : { "comments" : [  ],
"location" : "akra.terrain.Terrain",
"arguments" : [  ],
"type" : "bool",
"isInline" : true},
"_initSystemData" : { "comments" : [  ],
"location" : "akra.terrain.Terrain",
"arguments" : [  ],
"type" : "bool",
"isInline" : false},
"init" : { "comments" : [  ],
"location" : "akra.terrain.Terrain",
"arguments" : [ { "name" : "pMap",
"isOptional" : false,
"type" : "akra.IImageMap"},
{ "name" : "worldExtents",
"isOptional" : false,
"type" : "akra.IRect3d"},
{ "name" : "iShift",
"isOptional" : false,
"type" : "uint"},
{ "name" : "iShiftX",
"isOptional" : false,
"type" : "uint"},
{ "name" : "iShiftY",
"isOptional" : false,
"type" : "uint"},
{ "name" : "sSurfaceTextures",
"isOptional" : false,
"type" : "string"},
{ "name" : "pRootNode",
"isOptional" : true,
"type" : "akra.ISceneNode"} ],
"type" : "bool",
"isInline" : false},
"initMegaTexture" : { "comments" : [  ],
"location" : "akra.terrain.Terrain",
"arguments" : [ { "name" : "sSurfaceTextures",
"isOptional" : true,
"type" : "string"} ],
"type" : "void",
"isInline" : false},
"findSection" : { "comments" : [  ],
"location" : "akra.terrain.Terrain",
"arguments" : [ { "name" : "iX",
"isOptional" : false,
"type" : "uint"},
{ "name" : "iY",
"isOptional" : false,
"type" : "uint"} ],
"type" : "akra.ITerrainSection",
"isInline" : false},
"_allocateSectors" : { "comments" : [  ],
"location" : "akra.terrain.Terrain",
"arguments" : [  ],
"type" : "bool",
"isInline" : false},
"_setRenderMethod" : { "comments" : [  ],
"location" : "akra.terrain.Terrain",
"arguments" : [ { "name" : "pRenderMethod",
"isOptional" : false,
"type" : "akra.IRenderMethod"} ],
"type" : "void",
"isInline" : false},
"_buildHeightAndNormalTables" : { "comments" : [  ],
"location" : "akra.terrain.Terrain",
"arguments" : [ { "name" : "pImageHightMap",
"isOptional" : false,
"type" : "akra.IImg"},
{ "name" : "pImageNormalMap",
"isOptional" : false,
"type" : "akra.IImg"} ],
"type" : "void",
"isInline" : false},
"readWorldHeight" : { "comments" : [  ],
"location" : "akra.terrain.Terrain",
"arguments" : [ { "name" : "iMapX",
"isOptional" : false,
"type" : "uint"},
{ "name" : "iMapY",
"isOptional" : false,
"type" : "uint"} ],
"type" : "float",
"isInline" : false},
"readWorldNormal" : { "comments" : [  ],
"location" : "akra.terrain.Terrain",
"arguments" : [ { "name" : "v3fNormal",
"isOptional" : false,
"type" : "akra.IVec3"},
{ "name" : "iMapX",
"isOptional" : false,
"type" : "uint"},
{ "name" : "iMapY",
"isOptional" : false,
"type" : "uint"} ],
"type" : "akra.IVec3",
"isInline" : false},
"projectPoint" : { "comments" : [  ],
"location" : "akra.terrain.Terrain",
"arguments" : [ { "name" : "v3fCoord",
"isOptional" : false,
"type" : "akra.IVec3"},
{ "name" : "v3fDestenation",
"isOptional" : false,
"type" : "akra.IVec3"} ],
"type" : "bool",
"isInline" : false},
"prepareForRender" : { "comments" : [ [ "/**",
"* Подготовка терраина к рендерингу.",
"*/" ] ],
"location" : "akra.terrain.Terrain",
"arguments" : [ { "name" : "pViewport",
"isOptional" : false,
"type" : "akra.IViewport"} ],
"type" : "void",
"isInline" : false},
"reset" : { "comments" : [ [ "/**",
"* Сброс параметров.",
"*/" ] ],
"location" : "akra.terrain.Terrain",
"arguments" : [  ],
"type" : "void",
"isInline" : false},
"computeBaseNormal" : { "comments" : [  ],
"location" : "akra.terrain.Terrain",
"arguments" : [ { "name" : "pImageHightMap",
"isOptional" : false,
"type" : "akra.IImg"} ],
"type" : "void",
"isInline" : false},
"_tableIndex" : { "comments" : [  ],
"location" : "akra.terrain.Terrain",
"arguments" : [ { "name" : "iMapX",
"isOptional" : false,
"type" : "uint"},
{ "name" : "iMapY",
"isOptional" : false,
"type" : "uint"} ],
"type" : "uint",
"isInline" : false},
"_useVertexNormal" : { "comments" : [  ],
"location" : "akra.terrain.Terrain",
"arguments" : [  ],
"type" : "bool",
"isInline" : false},
"computeBoundingBox" : { "comments" : [  ],
"location" : "akra.terrain.Terrain",
"arguments" : [  ],
"type" : "void",
"isInline" : false},
"_onRender" : { "comments" : [  ],
"location" : "akra.terrain.Terrain",
"arguments" : [ { "name" : "pTechnique",
"isOptional" : false,
"type" : "akra.IRenderTechnique"},
{ "name" : "iPass",
"isOptional" : false,
"type" : "uint"} ],
"type" : "void",
"isInline" : false},
"_onGenerateNormalRender" : { "comments" : [  ],
"location" : "akra.terrain.Terrain",
"arguments" : [ { "name" : "pTechnique",
"isOptional" : false,
"type" : "akra.IRenderTechnique"},
{ "name" : "iPass",
"isOptional" : false,
"type" : "uint"} ],
"type" : "void",
"isInline" : false}},
"setters" : { "manualMegaTextureInit" : { "type" : "bool",
"inline" : true,
"location" : "akra.terrain.Terrain"},
"showMegaTexture" : { "type" : "bool",
"inline" : true,
"location" : "akra.terrain.Terrain"}}}