{ "location" : "akra.util",
"variables" : { "private" : { "bWebGL" : { "location" : "akra.util.ApiInfo",
"type" : "bool"},
"bWebAudio" : { "location" : "akra.util.ApiInfo",
"type" : "bool"},
"bFile" : { "location" : "akra.util.ApiInfo",
"type" : "bool"},
"bFileSystem" : { "location" : "akra.util.ApiInfo",
"type" : "bool"},
"bWebWorker" : { "location" : "akra.util.ApiInfo",
"type" : "bool"},
"bTransferableObjects" : { "location" : "akra.util.ApiInfo",
"type" : "bool"},
"bLocalStorage" : { "location" : "akra.util.ApiInfo",
"type" : "bool"},
"bWebSocket" : { "location" : "akra.util.ApiInfo",
"type" : "bool"},
"bGamepad" : { "location" : "akra.util.ApiInfo",
"type" : "bool"}}},
"getters" : { "webGL" : { "type" : "bool",
"isInline" : false,
"location" : "akra.util.ApiInfo"},
"transferableObjects" : { "type" : "bool",
"isInline" : false,
"location" : "akra.util.ApiInfo"},
"file" : { "type" : "bool",
"isInline" : false,
"location" : "akra.util.ApiInfo"},
"fileSystem" : { "type" : "bool",
"isInline" : false,
"location" : "akra.util.ApiInfo"},
"webAudio" : { "type" : "bool",
"isInline" : false,
"location" : "akra.util.ApiInfo"},
"webWorker" : { "type" : "bool",
"isInline" : false,
"location" : "akra.util.ApiInfo"},
"localStorage" : { "type" : "bool",
"isInline" : false,
"location" : "akra.util.ApiInfo"},
"webSocket" : { "type" : "bool",
"isInline" : false,
"location" : "akra.util.ApiInfo"},
"gamepad" : { "type" : "bool",
"isInline" : false,
"location" : "akra.util.ApiInfo"},
"zip" : { "type" : "bool",
"isInline" : false,
"location" : "akra.util.ApiInfo"}},
"constructors" : [ { "comments" : [  ],
"location" : "akra.util.ApiInfo",
"arguments" : [  ]} ],
"functions" : { "chechTransferableObjects" : { "comments" : [  ],
"location" : "akra.util.ApiInfo",
"arguments" : [  ],
"type" : "bool",
"isInline" : false}}}