{ "location" : "akra.util",
"variables" : { "private" : { "_iSize" : { "location" : "akra.util.ObjectSortCollection",
"type" : "uint"},
"_iCursor" : { "location" : "akra.util.ObjectSortCollection",
"type" : "uint"},
"_pElements" : { "location" : "akra.util.ObjectSortCollection",
"type" : "any"},
"_fnCollectionIndex" : { "location" : "akra.util.ObjectSortCollection",
"type" : "akra.ICollectionIndexFunction"},
"_iCursorElementIndex" : { "location" : "akra.util.ObjectSortCollection",
"type" : "int"},
"_iStartElementIndex" : { "location" : "akra.util.ObjectSortCollection",
"type" : "int"},
"_iLastElementIndex" : { "location" : "akra.util.ObjectSortCollection",
"type" : "int"}}},
"constructors" : [ { "comments" : [  ],
"location" : "akra.util.ObjectSortCollection",
"arguments" : [ { "name" : "iSize",
"isOptional" : false,
"type" : "uint"} ]} ],
"functions" : { "push" : { "comments" : [  ],
"location" : "akra.util.ObjectSortCollection",
"arguments" : [ { "name" : "pElement",
"isOptional" : false,
"type" : "any"} ],
"type" : "void",
"isInline" : false},
"findElement" : { "comments" : [  ],
"location" : "akra.util.ObjectSortCollection",
"arguments" : [ { "name" : "iCollectionIndex",
"isOptional" : false,
"type" : "int"} ],
"type" : "any",
"isInline" : false},
"takeElement" : { "comments" : [  ],
"location" : "akra.util.ObjectSortCollection",
"arguments" : [ { "name" : "iCollectionIndex",
"isOptional" : false,
"type" : "int"} ],
"type" : "any",
"isInline" : false},
"getElementAt" : { "comments" : [  ],
"location" : "akra.util.ObjectSortCollection",
"arguments" : [ { "name" : "iIndex",
"isOptional" : false,
"type" : "uint"} ],
"type" : "any",
"isInline" : true},
"setElementAt" : { "comments" : [  ],
"location" : "akra.util.ObjectSortCollection",
"arguments" : [ { "name" : "iIndex",
"isOptional" : false,
"type" : "uint"},
{ "name" : "pValue",
"isOptional" : false,
"type" : "any"} ],
"type" : "void",
"isInline" : true},
"removeElementAt" : { "comments" : [  ],
"location" : "akra.util.ObjectSortCollection",
"arguments" : [ { "name" : "iIndex",
"isOptional" : false,
"type" : "uint"} ],
"type" : "void",
"isInline" : true},
"clear" : { "comments" : [  ],
"location" : "akra.util.ObjectSortCollection",
"arguments" : [  ],
"type" : "void",
"isInline" : false},
"setCollectionFuncion" : { "comments" : [  ],
"location" : "akra.util.ObjectSortCollection",
"arguments" : [ { "name" : "fnCollection",
"isOptional" : false,
"type" : "akra.ICollectionIndexFunction"} ],
"type" : "void",
"isInline" : false}}}