{ "location" : "akra.fx",
"variables" : { "private" : { "_pConstructorType" : { "location" : "akra.fx.InitExprInstruction",
"type" : "akra.IAFXTypeInstruction"},
"_isConst" : { "location" : "akra.fx.InitExprInstruction",
"type" : "bool"},
"_isArray" : { "location" : "akra.fx.InitExprInstruction",
"type" : "bool"}}},
"constructors" : [ { "comments" : [  ],
"location" : "akra.fx.InitExprInstruction",
"arguments" : [  ]} ],
"functions" : { "toFinalCode" : { "comments" : [  ],
"location" : "akra.fx.InitExprInstruction",
"arguments" : [  ],
"type" : "string",
"isInline" : false},
"isConst" : { "comments" : [  ],
"location" : "akra.fx.InitExprInstruction",
"arguments" : [  ],
"type" : "bool",
"isInline" : false},
"optimizeForVariableType" : { "comments" : [  ],
"location" : "akra.fx.InitExprInstruction",
"arguments" : [ { "name" : "pType",
"isOptional" : false,
"type" : "akra.IAFXVariableTypeInstruction"} ],
"type" : "bool",
"isInline" : false},
"evaluate" : { "comments" : [  ],
"location" : "akra.fx.InitExprInstruction",
"arguments" : [  ],
"type" : "bool",
"isInline" : false}}}