{ "location" : "akra.ui.graph",
"variables" : { "public" : { "_pLeft" : { "location" : "akra.ui.graph.Route",
"type" : "IUIGraphConnector"},
"_pRight" : { "location" : "akra.ui.graph.Route",
"type" : "IUIGraphConnector"},
"_bActive" : { "location" : "akra.ui.graph.Route",
"type" : "bool"},
"_bHighlighted" : { "location" : "akra.ui.graph.Route",
"type" : "bool"},
"_pPath" : { "location" : "akra.ui.graph.Route",
"type" : "RaphaelPath"},
"_pArrow" : { "location" : "akra.ui.graph.Route",
"type" : "RaphaelPath"},
"_pColor" : { "location" : "akra.ui.graph.Route",
"type" : "IColor"},
"_pInactiveColor" : { "location" : "akra.ui.graph.Route",
"type" : "IColor"},
"_fWeight" : { "location" : "akra.ui.graph.Route",
"type" : "number"},
"_fMaxWeight" : { "location" : "akra.ui.graph.Route",
"type" : "number"}}},
"getters" : { "inactiveColor" : { "type" : "IColor",
"isInline" : true,
"location" : "akra.ui.graph.Route"},
"color" : { "type" : "IColor",
"isInline" : true,
"location" : "akra.ui.graph.Route"},
"left" : { "type" : "IUIGraphConnector",
"isInline" : true,
"location" : "akra.ui.graph.Route"},
"right" : { "type" : "IUIGraphConnector",
"isInline" : true,
"location" : "akra.ui.graph.Route"},
"weight" : { "type" : "number",
"isInline" : true,
"location" : "akra.ui.graph.Route"},
"arrow" : { "type" : "RaphaelPath",
"isInline" : true,
"location" : "akra.ui.graph.Route"},
"path" : { "type" : "RaphaelPath",
"isInline" : true,
"location" : "akra.ui.graph.Route"},
"canvas" : { "type" : "RaphaelPaper",
"isInline" : true,
"location" : "akra.ui.graph.Route"}},
"setters" : { "left" : { "type" : "IUIGraphConnector",
"inline" : false,
"location" : "akra.ui.graph.Route"},
"right" : { "type" : "IUIGraphConnector",
"inline" : false,
"location" : "akra.ui.graph.Route"},
"weight" : { "type" : "number",
"inline" : true,
"location" : "akra.ui.graph.Route"},
"arrow" : { "type" : "RaphaelPath",
"inline" : true,
"location" : "akra.ui.graph.Route"},
"path" : { "type" : "RaphaelPath",
"inline" : true,
"location" : "akra.ui.graph.Route"}},
"constructors" : [ { "comments" : [  ],
"location" : "akra.ui.graph.Route",
"arguments" : [ { "name" : "pLeft",
"isOptional" : false,
"type" : "IUIGraphConnector"},
{ "name" : "pRight",
"isOptional" : false,
"type" : "IUIGraphConnector"} ]} ],
"functions" : { "isConnectedWithNode" : { "comments" : [  ],
"location" : "akra.ui.graph.Route",
"arguments" : [ { "name" : "pNode",
"isOptional" : false,
"type" : "IUIGraphNode"} ],
"type" : "bool",
"isInline" : true},
"isConnectedWith" : { "comments" : [  ],
"location" : "akra.ui.graph.Route",
"arguments" : [ { "name" : "pConnector",
"isOptional" : false,
"type" : "IUIGraphConnector"} ],
"type" : "bool",
"isInline" : true},
"isBridge" : { "comments" : [  ],
"location" : "akra.ui.graph.Route",
"arguments" : [  ],
"type" : "bool",
"isInline" : true},
"isActive" : { "comments" : [  ],
"location" : "akra.ui.graph.Route",
"arguments" : [  ],
"type" : "bool",
"isInline" : true},
"detach" : { "comments" : [  ],
"location" : "akra.ui.graph.Route",
"arguments" : [  ],
"type" : "void",
"isInline" : false},
"remove" : { "comments" : [  ],
"location" : "akra.ui.graph.Route",
"arguments" : [ { "name" : "bRecirsive",
"isOptional" : true,
"type" : "bool"} ],
"type" : "void",
"isInline" : false},
"sendEvent" : { "comments" : [  ],
"location" : "akra.ui.graph.Route",
"arguments" : [ { "name" : "e",
"isOptional" : false,
"type" : "IUIGraphEvent"} ],
"type" : "void",
"isInline" : false},
"destroy" : { "comments" : [  ],
"location" : "akra.ui.graph.Route",
"arguments" : [  ],
"type" : "void",
"isInline" : false},
"activate" : { "comments" : [  ],
"location" : "akra.ui.graph.Route",
"arguments" : [ { "name" : "bValue",
"isOptional" : true,
"type" : "bool"} ],
"type" : "void",
"isInline" : false},
"routing" : { "comments" : [  ],
"location" : "akra.ui.graph.Route",
"arguments" : [  ],
"type" : "void",
"isInline" : false},
"drawRoute" : { "comments" : [ [ "/**@protected*/" ] ],
"location" : "akra.ui.graph.Route",
"arguments" : [ { "name" : "pFrom",
"isOptional" : false,
"type" : "IPoint"},
{ "name" : "pTo",
"isOptional" : false,
"type" : "IPoint"},
{ "name" : "eFromOr",
"isOptional" : true,
"type" : "EGraphConnectorOrient"},
{ "name" : "eToOr",
"isOptional" : true,
"type" : "EGraphConnectorOrient"} ],
"type" : "void",
"isInline" : false},
"calcPosition" : { "comments" : [  ],
"location" : "akra.ui.graph.Route",
"arguments" : [ { "name" : "pConnector",
"isOptional" : false,
"type" : "IUIGraphConnector"} ],
"type" : "IPoint",
"isInline" : false}}}