{ "location" : "akra.geometry",
"variables" : { "public" : { "normal" : { "location" : "akra.geometry.Plane3d",
"type" : "akra.IVec3"},
"distance" : { "location" : "akra.geometry.Plane3d",
"type" : "float"}}},
"constructors" : [ { "comments" : [  ],
"location" : "akra.geometry.Plane3d",
"arguments" : [  ]},
{ "comments" : [  ],
"location" : "akra.geometry.Plane3d",
"arguments" : [ { "name" : "pPlane",
"isOptional" : false,
"type" : "akra.IPlane3d"} ]},
{ "comments" : [  ],
"location" : "akra.geometry.Plane3d",
"arguments" : [ { "name" : "v3fNormal",
"isOptional" : false,
"type" : "akra.IVec3"},
{ "name" : "fDistance",
"isOptional" : false,
"type" : "float"} ]},
{ "comments" : [  ],
"location" : "akra.geometry.Plane3d",
"arguments" : [ { "name" : "v3fPoint1",
"isOptional" : false,
"type" : "akra.IVec3"},
{ "name" : "v3fPoint2",
"isOptional" : false,
"type" : "akra.IVec3"},
{ "name" : "v3fPoint3",
"isOptional" : false,
"type" : "akra.IVec3"} ]} ],
"functions" : { "set" : { "comments" : [  ],
"location" : "akra.geometry.Plane3d",
"arguments" : [ { "name" : "v3fPoint1",
"isOptional" : false,
"type" : "akra.IVec3"},
{ "name" : "v3fPoint2",
"isOptional" : false,
"type" : "akra.IVec3"},
{ "name" : "v3fPoint3",
"isOptional" : false,
"type" : "akra.IVec3"} ],
"type" : "akra.IPlane3d",
"isInline" : false},
"clear" : { "comments" : [  ],
"location" : "akra.geometry.Plane3d",
"arguments" : [  ],
"type" : "akra.IPlane3d",
"isInline" : true},
"negate" : { "comments" : [  ],
"location" : "akra.geometry.Plane3d",
"arguments" : [  ],
"type" : "akra.IPlane3d",
"isInline" : true},
"normalize" : { "comments" : [  ],
"location" : "akra.geometry.Plane3d",
"arguments" : [  ],
"type" : "akra.IPlane3d",
"isInline" : false},
"isEqual" : { "comments" : [  ],
"location" : "akra.geometry.Plane3d",
"arguments" : [ { "name" : "pPlane",
"isOptional" : false,
"type" : "akra.IPlane3d"} ],
"type" : "bool",
"isInline" : false},
"projectPointToPlane" : { "comments" : [  ],
"location" : "akra.geometry.Plane3d",
"arguments" : [ { "name" : "v3fPoint",
"isOptional" : false,
"type" : "akra.IVec3"},
{ "name" : "v3fDestination",
"isOptional" : true,
"type" : "akra.IVec3"} ],
"type" : "akra.IVec3",
"isInline" : false},
"solveForX" : { "comments" : [  ],
"location" : "akra.geometry.Plane3d",
"arguments" : [ { "name" : "fY",
"isOptional" : false,
"type" : "float"},
{ "name" : "fZ",
"isOptional" : false,
"type" : "float"} ],
"type" : "float",
"isInline" : false},
"solveForY" : { "comments" : [  ],
"location" : "akra.geometry.Plane3d",
"arguments" : [ { "name" : "fX",
"isOptional" : false,
"type" : "float"},
{ "name" : "fZ",
"isOptional" : false,
"type" : "float"} ],
"type" : "float",
"isInline" : false},
"solveForZ" : { "comments" : [  ],
"location" : "akra.geometry.Plane3d",
"arguments" : [ { "name" : "fX",
"isOptional" : false,
"type" : "float"},
{ "name" : "fY",
"isOptional" : false,
"type" : "float"} ],
"type" : "float",
"isInline" : false},
"intersectRay3d" : { "comments" : [  ],
"location" : "akra.geometry.Plane3d",
"arguments" : [ { "name" : "pRay",
"isOptional" : false,
"type" : "akra.IRay3d"},
{ "name" : "vDest",
"isOptional" : false,
"type" : "akra.IVec3"} ],
"type" : "bool",
"isInline" : false},
"signedDistance" : { "comments" : [  ],
"location" : "akra.geometry.Plane3d",
"arguments" : [ { "name" : "v3fPoint",
"isOptional" : false,
"type" : "akra.IVec3"} ],
"type" : "float",
"isInline" : false},
"toString" : { "comments" : [  ],
"location" : "akra.geometry.Plane3d",
"arguments" : [  ],
"type" : "string",
"isInline" : false}}}