{ "location" : "akra",
"functions" : { "getType" : { "comments" : [  ],
"location" : "akra.ICodec",
"arguments" : [  ],
"type" : "string",
"isInline" : false},
"getDataType" : { "comments" : [  ],
"location" : "akra.ICodec",
"arguments" : [  ],
"type" : "string",
"isInline" : false},
"magicNumberMatch" : { "comments" : [  ],
"location" : "akra.ICodec",
"arguments" : [ { "name" : "pMagicNumber",
"isOptional" : false,
"type" : "Uint8Array"} ],
"type" : "bool",
"isInline" : false},
"magicNumberToFileExt" : { "comments" : [  ],
"location" : "akra.ICodec",
"arguments" : [ { "name" : "pMagicNumber",
"isOptional" : false,
"type" : "Uint8Array"} ],
"type" : "string",
"isInline" : false},
"code" : { "comments" : [  ],
"location" : "akra.ICodec",
"arguments" : [ { "name" : "pInput",
"isOptional" : false,
"type" : "Uint8Array"},
{ "name" : "pData",
"isOptional" : false,
"type" : "akra.ICodecData"} ],
"type" : "Uint8Array",
"isInline" : false},
"decode" : { "comments" : [  ],
"location" : "akra.ICodec",
"arguments" : [ { "name" : "pData",
"isOptional" : false,
"type" : "Uint8Array"},
{ "name" : "pCodecData",
"isOptional" : false,
"type" : "akra.ICodecData"} ],
"type" : "Uint8Array",
"isInline" : false}}}