{ "location" : "akra",
"variables" : { "public" : { "asset" : { "location" : "akra.IColladaDocument",
"type" : "akra.IColladaAsset"},
"libEffects" : { "location" : "akra.IColladaDocument",
"type" : "akra.IColladaEffectLibrary"},
"libMaterials" : { "location" : "akra.IColladaDocument",
"type" : "akra.IColladaLibrary"},
"libGeometries" : { "location" : "akra.IColladaDocument",
"type" : "akra.IColladaLibrary"},
"libVisualScenes" : { "location" : "akra.IColladaDocument",
"type" : "akra.IColladaLibrary"},
"libAnimations" : { "location" : "akra.IColladaDocument",
"type" : "akra.IColladaLibrary"},
"scene" : { "location" : "akra.IColladaDocument",
"type" : "akra.IColladaScene"}}}}