{ "location" : "akra",
"variables" : { "public" : { "asset" : { "location" : "akra.IColladaDocument",
"type" : "IColladaAsset"},
"libEffects" : { "location" : "akra.IColladaDocument",
"type" : "IColladaEffectLibrary"},
"libMaterials" : { "location" : "akra.IColladaDocument",
"type" : "IColladaLibrary"},
"libGeometries" : { "location" : "akra.IColladaDocument",
"type" : "IColladaLibrary"},
"libVisualScenes" : { "location" : "akra.IColladaDocument",
"type" : "IColladaLibrary"},
"libAnimations" : { "location" : "akra.IColladaDocument",
"type" : "IColladaLibrary"},
"scene" : { "location" : "akra.IColladaDocument",
"type" : "IColladaScene"}}}}