{ "location" : "akra",
"functions" : { "init" : { "comments" : [  ],
"location" : "akra.ILogger",
"arguments" : [  ],
"type" : "bool",
"isInline" : false},
"setLogLevel" : { "comments" : [  ],
"location" : "akra.ILogger",
"arguments" : [ { "name" : "eLevel",
"isOptional" : false,
"type" : "ELogLevel"} ],
"type" : "void",
"isInline" : false},
"getLogLevel" : { "comments" : [  ],
"location" : "akra.ILogger",
"arguments" : [  ],
"type" : "ELogLevel",
"isInline" : false},
"registerCode" : { "comments" : [  ],
"location" : "akra.ILogger",
"arguments" : [ { "name" : "eCode",
"isOptional" : false,
"type" : "number"},
{ "name" : "sMessage",
"isOptional" : true,
"type" : "string"} ],
"type" : "bool",
"isInline" : false},
"setUnknownCode" : { "comments" : [  ],
"location" : "akra.ILogger",
"arguments" : [ { "name" : "eCode",
"isOptional" : false,
"type" : "number"},
{ "name" : "sMessage",
"isOptional" : false,
"type" : "string"} ],
"type" : "void",
"isInline" : false},
"registerCodeFamily" : { "comments" : [  ],
"location" : "akra.ILogger",
"arguments" : [ { "name" : "eCodeMin",
"isOptional" : false,
"type" : "number"},
{ "name" : "eCodeMax",
"isOptional" : false,
"type" : "number"},
{ "name" : "sFamilyName",
"isOptional" : true,
"type" : "string"} ],
"type" : "bool",
"isInline" : false},
"getFamilyName" : { "comments" : [  ],
"location" : "akra.ILogger",
"arguments" : [ { "name" : "eCode",
"isOptional" : false,
"type" : "number"} ],
"type" : "string",
"isInline" : false},
"setCodeFamilyRoutine" : { "comments" : [  ],
"location" : "akra.ILogger",
"arguments" : [ { "name" : "sFamilyName",
"isOptional" : false,
"type" : "string"},
{ "name" : "fnLogRoutine",
"isOptional" : false,
"type" : "ILogRoutineFunc"},
{ "name" : "eLevel",
"isOptional" : false,
"type" : "ELogLevel"} ],
"type" : "bool",
"isInline" : false},
"setLogRoutine" : { "comments" : [  ],
"location" : "akra.ILogger",
"arguments" : [ { "name" : "fnLogRoutine",
"isOptional" : false,
"type" : "ILogRoutineFunc"},
{ "name" : "eLevel",
"isOptional" : false,
"type" : "ELogLevel"} ],
"type" : "void",
"isInline" : false},
"setSourceLocation" : { "comments" : [  ],
"location" : "akra.ILogger",
"arguments" : [ { "name" : "pLocation",
"isOptional" : false,
"type" : "ISourceLocation"} ],
"type" : "void",
"isInline" : false},
"log" : { "comments" : [  ],
"location" : "akra.ILogger",
"arguments" : [ { "name" : "..."},
{ "name" : "pArgs",
"isOptional" : false,
"type" : "[  ]"} ],
"variableArgList" : true,
"type" : "any",
"isInline" : false},
"info" : { "comments" : [  ],
"location" : "akra.ILogger",
"arguments" : [ { "name" : "..."},
{ "name" : "pArgs",
"isOptional" : false,
"type" : "[  ]"} ],
"variableArgList" : true,
"type" : "void",
"isInline" : false},
"warning" : { "comments" : [  ],
"location" : "akra.ILogger",
"arguments" : [ { "name" : "..."},
{ "name" : "pArgs",
"isOptional" : false,
"type" : "[  ]"} ],
"variableArgList" : true,
"type" : "void",
"isInline" : false},
"error" : { "comments" : [  ],
"location" : "akra.ILogger",
"arguments" : [ { "name" : "..."},
{ "name" : "pArgs",
"isOptional" : false,
"type" : "[  ]"} ],
"variableArgList" : true,
"type" : "void",
"isInline" : false},
"criticalError" : { "comments" : [  ],
"location" : "akra.ILogger",
"arguments" : [ { "name" : "..."},
{ "name" : "pArgs",
"isOptional" : false,
"type" : "[  ]"} ],
"variableArgList" : true,
"type" : "void",
"isInline" : false},
"assert" : { "comments" : [  ],
"location" : "akra.ILogger",
"arguments" : [ { "name" : "bCondition",
"isOptional" : false,
"type" : "bool"},
{ "name" : "..."},
{ "name" : "pArgs",
"isOptional" : false,
"type" : "[  ]"} ],
"variableArgList" : true,
"type" : "void",
"isInline" : false}}}