{ "location" : "akra",
"variables" : { "public" : { "name" : { "location" : "akra.IPixelFormatDescription",
"type" : "string"},
"elemBytes" : { "location" : "akra.IPixelFormatDescription",
"type" : "number"},
"flags" : { "location" : "akra.IPixelFormatDescription",
"type" : "number"},
"componentType" : { "location" : "akra.IPixelFormatDescription",
"type" : "EPixelComponentTypes"},
"componentCount" : { "location" : "akra.IPixelFormatDescription",
"type" : "number"},
"rbits" : { "location" : "akra.IPixelFormatDescription",
"type" : "number"},
"gbits" : { "location" : "akra.IPixelFormatDescription",
"type" : "number"},
"bbits" : { "location" : "akra.IPixelFormatDescription",
"type" : "number"},
"abits" : { "location" : "akra.IPixelFormatDescription",
"type" : "number"},
"rmask" : { "location" : "akra.IPixelFormatDescription",
"type" : "number"},
"gmask" : { "location" : "akra.IPixelFormatDescription",
"type" : "number"},
"bmask" : { "location" : "akra.IPixelFormatDescription",
"type" : "number"},
"amask" : { "location" : "akra.IPixelFormatDescription",
"type" : "number"},
"rshift" : { "location" : "akra.IPixelFormatDescription",
"type" : "number"},
"gshift" : { "location" : "akra.IPixelFormatDescription",
"type" : "number"},
"bshift" : { "location" : "akra.IPixelFormatDescription",
"type" : "number"},
"ashift" : { "location" : "akra.IPixelFormatDescription",
"type" : "number"}}}}